LICENSE
MANIFEST.in
README.md
setup.py
django_package_template/__init__.py
django_package_template/admin.py
django_package_template/apps.py
django_package_template/models.py
django_package_template/tests.py
django_package_template/views.py
django_package_template.egg-info/PKG-INFO
django_package_template.egg-info/SOURCES.txt
django_package_template.egg-info/dependency_links.txt
django_package_template.egg-info/top_level.txt
django_package_template/migrations/__init__.py